cryovit/__init__.py
cryovit/_logging_config.py
cryovit/_version.py
cryovit/config.py
cryovit/types.py
cryovit/utils.py
cryovit/cli/__init__.py
cryovit/cli/cli.py
cryovit/cli/dino_cli.py
cryovit/cli/eval_cli.py
cryovit/cli/infer_cli.py
cryovit/cli/train_cli.py
cryovit/configs/dino_features.yaml
cryovit/configs/eval_model.yaml
cryovit/configs/infer_model.yaml
cryovit/configs/train_model.yaml
cryovit/configs/callbacks/csv_writer.yaml
cryovit/configs/callbacks/rich_progress_bar.yaml
cryovit/configs/callbacks/stochastic_weight_average.yaml
cryovit/configs/callbacks/test_pred_writer.yaml
cryovit/configs/datamodule/dino.yaml
cryovit/configs/datamodule/file.yaml
cryovit/configs/datamodule/fractional.yaml
cryovit/configs/datamodule/fractional_loo.yaml
cryovit/configs/datamodule/multi.yaml
cryovit/configs/datamodule/single.yaml
cryovit/configs/datamodule/dataloader/default.yaml
cryovit/configs/datamodule/dataset/file.yaml
cryovit/configs/datamodule/dataset/tomo.yaml
cryovit/configs/datamodule/dataset/vit.yaml
cryovit/configs/experiments/fibro_cancer_to_neuron_mito.yaml
cryovit/configs/experiments/fractional_bacteria.yaml
cryovit/configs/experiments/fractional_cristae.yaml
cryovit/configs/experiments/fractional_granule.yaml
cryovit/configs/experiments/fractional_microtubule.yaml
cryovit/configs/experiments/fractional_mito.yaml
cryovit/configs/experiments/hd_to_healthy_mito.yaml
cryovit/configs/experiments/healthy_to_hd_mito.yaml
cryovit/configs/experiments/multi_bacteria.yaml
cryovit/configs/experiments/multi_cristae.yaml
cryovit/configs/experiments/multi_granule.yaml
cryovit/configs/experiments/multi_microtubule.yaml
cryovit/configs/experiments/multi_mito.yaml
cryovit/configs/experiments/neuron_to_fibro_cancer_mito.yaml
cryovit/configs/experiments/old_to_young_mito.yaml
cryovit/configs/experiments/sam2_hparams.yaml
cryovit/configs/experiments/single_ad_mito.yaml
cryovit/configs/experiments/single_algae_mito.yaml
cryovit/configs/experiments/single_hd_dense_mito.yaml
cryovit-0.1.3.dist-info/licenses/LICENSE
cryovit-0.1.3.dist-info/METADATA
cryovit-0.1.3.dist-info/WHEEL
cryovit-0.1.3.dist-info/entry_points.txt
cryovit-0.1.3.dist-info/top_level.txt
cryovit-0.1.3.dist-info/RECORD
