Metadata-Version: 2.4
Name: cryovit
Version: 0.1.3
Summary: Deep learning automated segmentation models using high-level features from foundation ViT models.
Author-email: Vivian Li <vdl21@cantab.ac.uk>, Sanket Rajan Gupte <sanketg@stanford.edu>
License: MIT License
Classifier: Development Status :: 2 - Pre-Alpha
Classifier: Intended Audience :: Developers
Classifier: License :: OSI Approved :: BSD License
Classifier: Operating System :: OS Independent
Classifier: Programming Language :: Python
Classifier: Programming Language :: Python :: 3
Classifier: Programming Language :: Python :: 3 :: Only
Classifier: Programming Language :: Python :: 3.10
Classifier: Programming Language :: Python :: 3.11
Classifier: Programming Language :: Python :: 3.12
Classifier: Programming Language :: Python :: 3.13
Classifier: Topic :: Scientific/Engineering :: Image Processing
Requires-Python: >=3.10
License-File: LICENSE
Requires-Dist: numpy==2.2.6
Requires-Dist: scipy==1.15.2
Requires-Dist: pandas==2.3.1
Requires-Dist: scikit-learn==1.3.2
Requires-Dist: h5py==3.14.0
Requires-Dist: mrcfile==1.5.4
Requires-Dist: tifffile==2025.5.10
Requires-Dist: rich==14.0.0
Requires-Dist: torch==2.7.1
Requires-Dist: torchvision==0.22.0
Requires-Dist: torchmetrics==1.8.0
Requires-Dist: pytorch-lightning==2.5.2
Requires-Dist: xformers==0.0.31
Requires-Dist: sam2==1.0.0
Requires-Dist: tensordict==0.9.1
Requires-Dist: hydra-core==1.3.2
Requires-Dist: mkl==2024.2.0
Requires-Dist: typer
Provides-Extra: dev
Requires-Dist: wandb>=0.21.0; extra == "dev"
Requires-Dist: huggingface_hub>=0.34.3; extra == "dev"
Requires-Dist: opencv>=4.12.0; extra == "dev"
Requires-Dist: scikit-learn>=1.3.2; extra == "dev"
Requires-Dist: umap-learn>=0.5.9; extra == "dev"
Requires-Dist: matplotlib>=3.10.5; extra == "dev"
Requires-Dist: seaborn>=0.13.2; extra == "dev"
Requires-Dist: mypy>=1.17.0; extra == "dev"
Dynamic: license-file
